<?xml version="1.0"?>
<fonts>

        <fontCodePoint>
            <code>113 846</code>
            <codeCap>81 846</codeCap>
        </fontCodePoint>
        <fontCodePoint>
            <code>119 846</code>
            <codeCap>87 846</codeCap>
        </fontCodePoint>
        <fontCodePoint>
            <code>101 846</code>
            <codeCap>69 846</codeCap>
        </fontCodePoint>
        <fontCodePoint>
            <code>114 846</code>
            <codeCap>82 846</codeCap>
        </fontCodePoint>
        <fontCodePoint>
            <code>116 846</code>
            <codeCap>84 846</codeCap>
        </fontCodePoint>
        <fontCodePoint>
            <code>121 846</code>
            <codeCap>89 846</codeCap>
        </fontCodePoint>
        <fontCodePoint>
            <code>117 846</code>
            <codeCap>85 846</codeCap>
        </fontCodePoint>
        <fontCodePoint>
            <code>105 846</code>
            <codeCap>73 846</codeCap>
        </fontCodePoint>
        <fontCodePoint>
            <code>111 846</code>
            <codeCap>79 846</codeCap>
        </fontCodePoint>
        <fontCodePoint>
            <code>112 846</code>
            <codeCap>80 846</codeCap>
        </fontCodePoint>
    <fontCodePoint>
        <code>97 846</code>
        <codeCap>65 846</codeCap>
    </fontCodePoint>
    <fontCodePoint>
        <code>115 846</code>
        <codeCap>83 846</codeCap>
    </fontCodePoint>
    <fontCodePoint>
        <code>100 846</code>
        <codeCap>68 846</codeCap>
    </fontCodePoint>
    <fontCodePoint>
        <code>102 846</code>
        <codeCap>70 846</codeCap>
    </fontCodePoint>
    <fontCodePoint>
        <code>103 846</code>
        <codeCap>71 846</codeCap>
    </fontCodePoint>
    <fontCodePoint>
        <code>104 846</code>
        <codeCap>72 846</codeCap>
    </fontCodePoint>
    <fontCodePoint>
        <code>106 846</code>
        <codeCap>74 846</codeCap>
    </fontCodePoint>
    <fontCodePoint>
        <code>107 846</code>
        <codeCap>75 846</codeCap>
    </fontCodePoint>
    <fontCodePoint>
        <code>108 846</code>
        <codeCap>76 846</codeCap>
    </fontCodePoint>
    <fontCodePoint>
        <code>122 846</code>
        <codeCap>90 846</codeCap>
    </fontCodePoint>
    <fontCodePoint>
        <code>120 846</code>
        <codeCap>88 846</codeCap>
    </fontCodePoint>
    <fontCodePoint>
        <code>99 846</code>
        <codeCap>67 846</codeCap>
    </fontCodePoint>
    <fontCodePoint>
        <code>118 846</code>
        <codeCap>86 846</codeCap>
    </fontCodePoint>
    <fontCodePoint>
        <code>98 846</code>
        <codeCap>66 846</codeCap>
    </fontCodePoint>
    <fontCodePoint>
        <code>110 846</code>
        <codeCap>78 846</codeCap>
    </fontCodePoint>
    <fontCodePoint>
        <code>109 846</code>
        <codeCap>77 846</codeCap>
    </fontCodePoint>

</fonts>